glasbeyish/__init__.py
glasbeyish/glasbey.py
glasbeyish-0.2.0.dist-info/licenses/LICENSE
glasbeyish-0.2.0.dist-info/METADATA
glasbeyish-0.2.0.dist-info/WHEEL
glasbeyish-0.2.0.dist-info/top_level.txt
glasbeyish-0.2.0.dist-info/RECORD
