Metadata-Version: 2.4
Name: glasbeyish
Version: 0.2.0
Summary: A library for generating color palettes with distinct colors
Author-email: Andrew Tapia <andrew.tapia@uky.edu>
Project-URL: Homepage, https://github.com/actapia/glasbeyish
Project-URL: Bug Tracker, https://github.com/actapia/glasbeyish
Classifier: Programming Language :: Python :: 3
Classifier: License :: OSI Approved :: MIT License
Classifier: Operating System :: OS Independent
Requires-Python: >=3.11
License-File: LICENSE
Requires-Dist: heap-mapping>=0.1.0
Requires-Dist: multiset-key-dict>=0.2.1
Requires-Dist: nice-colorsys>=0.2.0
Requires-Dist: numpy
Requires-Dist: hsluv
Dynamic: license-file
